{"pageContext":{"slug":"herrajes-y-platinas","name":"Herrajes y Platinas","image":{"publicURL":"/static/material.test-bd790dd28a01f3cfbce5fe87cde67ca3.jpg"},"content":[{"item":"Tapacantos Rehau","thickness":null,"measure":"22mm x 0.45mm, 22mm x 2mm, 45mm x 0.45mm","link":null,"desc":"pvc, pvc con adhesivo, melaminico con adhesivo","subItems":null},{"item":"Herrajes para muebles de cocina y placares","thickness":null,"measure":null,"link":null,"desc":"Correderas, bisagras, perfiles, manijas, tiradores, etc.","subItems":null},{"item":"Platinas","thickness":null,"measure":null,"link":null,"desc":null,"subItems":null}]}}